winrt/_winrt_windows_graphics_directx_direct3d11_interop.cp312-win_amd64.pyd
winrt/_winrt_windows_graphics_directx_direct3d11_interop.pyi
winrt/windows/graphics/directx/direct3d11/interop/__init__.py
winrt/windows/graphics/directx/direct3d11/interop/py.typed
winrt_windows_graphics_directx_direct3d11_interop-3.2.1.dist-info/METADATA
winrt_windows_graphics_directx_direct3d11_interop-3.2.1.dist-info/WHEEL
winrt_windows_graphics_directx_direct3d11_interop-3.2.1.dist-info/top_level.txt
winrt_windows_graphics_directx_direct3d11_interop-3.2.1.dist-info/RECORD
